[
  {
    "name": "Иностранный язык",
    "element_type": "discipline",
    "part": "mandatory",
    "credits": 12.0,
    "semesters": [1, 2, 3, 4, 5, 6],
    "source": "poop",
    "competency_codes": ["УК-3", "УК-4"]
  },
  {
    "name": "Программирование",
    "element_type": "discipline",
    "part": "mandatory",
    "credits": 18.0,
    "semesters": [1, 2, 3],
    "source": "poop",
    "competency_codes": ["ОПК-2", "ОПК-5", "ОПК-6", "ПК-7"]
  },
  {
    "name": "Математический анализ",
    "element_type": "discipline",
    "part": "mandatory",
    "credits": 5.0,
    "semesters": [1],
    "source": "poop",
    "competency_codes": ["ОПК-1"]
  },
  {
    "name": "Аналитическая геометрия",
    "element_type": "discipline",
    "part": "mandatory",
    "credits": 4.0,
    "semesters": [1],
    "source": "poop",
    "competency_codes": ["ОПК-1"]
  },
  {
    "name": "История",
    "element_type": "discipline",
    "part": "mandatory",
    "credits": 3.0,
    "semesters": [2],
    "source": "poop",
    "competency_codes": ["УК-5"]
  },
  {
    "name": "Философия",
    "element_type": "discipline",
    "part": "mandatory",
    "credits": 3.0,
    "semesters": [4],
    "source": "poop",
    "competency_codes": ["УК-5"]
  },
  {
    "name": "Экономика",
    "element_type": "discipline",
    "part": "mandatory",
    "credits": 4.0,
    "semesters": [6, 7],
    "source": "poop",
    "competency_codes": ["ПК-1"]
  },
  {
    "name": "научно-исследовательская работа",
    "element_type": "practice",
    "part": "mandatory",
    "credits": 2.0,
    "semesters": [7],
    "source": "poop",
    "competency_codes": ["УК-1", "ОПК-1"]
  },
  {
    "name": "научно-исследовательская работа (получение первичных навыков научно-исследовательской работы)",
    "element_type": "practice",
    "part": "mandatory",
    "credits": 2.0,
    "semesters": [4],
    "source": "poop",
    "competency_codes": ["ОПК-1"]
  },
  {
    "name": "ознакомительная практика",
    "element_type": "practice",
    "part": "mandatory",
    "credits": 2.0,
    "semesters": [2],
    "source": "poop",
    "competency_codes": ["ПК-10"]
  },
  {
    "name": "технологическая (проектно-технологическая) практика",
    "element_type": "practice",
    "part": "mandatory",
    "credits": 2.0,
    "semesters": [4],
    "source": "poop",
    "competency_codes": ["ПК-11"]
  },
  {
    "name": "технологическая (проектно-технологическая) практика",
    "element_type": "practice",
    "part": "mandatory",
    "credits": 3.0,
    "semesters": [5],
    "source": "poop",
    "competency_codes": ["ПК-11"]
  },
  {
    "name": "эксплуатационная практика",
    "element_type": "practice",
    "part": "mandatory",
    "credits": 3.0,
    "semesters": [6],
    "source": "poop",
    "competency_codes": ["ПК-12"]
  },
  {
    "name": "эксплуатационная практика",
    "element_type": "practice",
    "part": "mandatory",
    "credits": 2.0,
    "semesters": [7],
    "source": "poop",
    "competency_codes": ["ПК-12"]
  }
]
